{
  "$schema": "https://developer.microsoft.com/json-schemas/fabric/item/report/definition/visualContainer/2.4.0/schema.json",
  "name": "a567c2cdb86780d00b02",
  "position": {
    "x": 76.893203883495147,
    "y": 298.25242718446549,
    "z": 4000,
    "height": 184.85436893203882,
    "width": 239.22330097087377,
    "tabOrder": 2000
  },
  "visual": {
    "visualType": "donutChart",
    "query": {
      "queryState": {
        "Category": {
          "projections": [
            {
              "field": {
                "Column": {
                  "Expression": {
                    "SourceRef": {
                      "Entity": "Customer Lookup"
                    }
                  },
                  "Property": "Income Level"
                }
              },
              "queryRef": "Customer Lookup.Income Level",
              "nativeQueryRef": "Income Level",
              "active": true
            }
          ]
        },
        "Y": {
          "projections": [
            {
              "field": {
                "Measure": {
                  "Expression": {
                    "SourceRef": {
                      "Entity": "Measure Table"
                    }
                  },
                  "Property": "Total Orders"
                }
              },
              "queryRef": "Measure Table.Total Orders",
              "nativeQueryRef": "Total Orders"
            }
          ]
        }
      },
      "sortDefinition": {
        "sort": [
          {
            "field": {
              "Measure": {
                "Expression": {
                  "SourceRef": {
                    "Entity": "Measure Table"
                  }
                },
                "Property": "Total Orders"
              }
            },
            "direction": "Descending"
          }
        ],
        "isDefaultSort": true
      }
    },
    "objects": {
      "legend": [
        {
          "properties": {
            "show": {
              "expr": {
                "Literal": {
                  "Value": "false"
                }
              }
            }
          }
        }
      ],
      "labels": [
        {
          "properties": {
            "labelStyle": {
              "expr": {
                "Literal": {
                  "Value": "'Both'"
                }
              }
            },
            "fontSize": {
              "expr": {
                "Literal": {
                  "Value": "8D"
                }
              }
            },
            "labelPrecision": {
              "expr": {
                "Literal": {
                  "Value": "1L"
                }
              }
            },
            "labelDisplayUnits": {
              "expr": {
                "Literal": {
                  "Value": "0D"
                }
              }
            }
          }
        }
      ],
      "dataPoint": [
        {
          "properties": {
            "fill": {
              "solid": {
                "color": {
                  "expr": {
                    "Literal": {
                      "Value": "'#1EDFE2'"
                    }
                  }
                }
              }
            }
          },
          "selector": {
            "data": [
              {
                "scopeId": {
                  "Comparison": {
                    "ComparisonKind": 0,
                    "Left": {
                      "Column": {
                        "Expression": {
                          "SourceRef": {
                            "Entity": "Customer Lookup"
                          }
                        },
                        "Property": "Income Level"
                      }
                    },
                    "Right": {
                      "Literal": {
                        "Value": "'Average'"
                      }
                    }
                  }
                }
              }
            ]
          }
        },
        {
          "properties": {
            "fill": {
              "solid": {
                "color": {
                  "expr": {
                    "ThemeDataColor": {
                      "ColorId": 1,
                      "Percent": 0.2
                    }
                  }
                }
              }
            }
          },
          "selector": {
            "data": [
              {
                "scopeId": {
                  "Comparison": {
                    "ComparisonKind": 0,
                    "Left": {
                      "Column": {
                        "Expression": {
                          "SourceRef": {
                            "Entity": "Customer Lookup"
                          }
                        },
                        "Property": "Income Level"
                      }
                    },
                    "Right": {
                      "Literal": {
                        "Value": "'Low'"
                      }
                    }
                  }
                }
              }
            ]
          }
        },
        {
          "properties": {
            "fill": {
              "solid": {
                "color": {
                  "expr": {
                    "ThemeDataColor": {
                      "ColorId": 8,
                      "Percent": 0.2
                    }
                  }
                }
              }
            }
          },
          "selector": {
            "data": [
              {
                "scopeId": {
                  "Comparison": {
                    "ComparisonKind": 0,
                    "Left": {
                      "Column": {
                        "Expression": {
                          "SourceRef": {
                            "Entity": "Customer Lookup"
                          }
                        },
                        "Property": "Income Level"
                      }
                    },
                    "Right": {
                      "Literal": {
                        "Value": "'High'"
                      }
                    }
                  }
                }
              }
            ]
          }
        }
      ]
    },
    "visualContainerObjects": {
      "title": [
        {
          "properties": {
            "fontFamily": {
              "expr": {
                "Literal": {
                  "Value": "'''Segoe UI'', wf_segoe-ui_normal, helvetica, arial, sans-serif'"
                }
              }
            },
            "alignment": {
              "expr": {
                "Literal": {
                  "Value": "'center'"
                }
              }
            },
            "text": {
              "expr": {
                "Literal": {
                  "Value": "'Orders by Income Level'"
                }
              }
            },
            "fontSize": {
              "expr": {
                "Literal": {
                  "Value": "10D"
                }
              }
            }
          }
        }
      ]
    },
    "drillFilterOtherVisuals": true
  },
  "filterConfig": {
    "filters": [
      {
        "name": "833e19e936614bdb3041",
        "field": {
          "Column": {
            "Expression": {
              "SourceRef": {
                "Entity": "Customer Lookup"
              }
            },
            "Property": "Income Level"
          }
        },
        "type": "Categorical",
        "filter": {
          "Version": 2,
          "From": [
            {
              "Name": "c",
              "Entity": "Customer Lookup",
              "Type": 0
            }
          ],
          "Where": [
            {
              "Condition": {
                "In": {
                  "Expressions": [
                    {
                      "Column": {
                        "Expression": {
                          "SourceRef": {
                            "Source": "c"
                          }
                        },
                        "Property": "Income Level"
                      }
                    }
                  ],
                  "Values": [
                    [
                      {
                        "Literal": {
                          "Value": "'Average'"
                        }
                      }
                    ],
                    [
                      {
                        "Literal": {
                          "Value": "'High'"
                        }
                      }
                    ],
                    [
                      {
                        "Literal": {
                          "Value": "'Low'"
                        }
                      }
                    ]
                  ]
                }
              }
            }
          ]
        }
      }
    ]
  }
}